autoscale_queue_celery/__init__.py
autoscale_queue_celery-0.2.0.dist-info/LICENSE
autoscale_queue_celery-0.2.0.dist-info/METADATA
autoscale_queue_celery-0.2.0.dist-info/WHEEL
autoscale_queue_celery-0.2.0.dist-info/RECORD
